{
 "model": {
    "kind": "model",
    "name": "description",
    "title": "Description",
    "description": "To provide comments about the node.",
    "javaType": "org.apache.camel.model.DescriptionDefinition",
    "label": "configuration",
    "deprecated": "false",
    "input": "false",
    "output": "false"
  },
  "properties": {
    "lang": { "kind": "attribute", "required": "false", "type": "string", "javaType": "java.lang.String", "deprecated": "false", "secret": "false", "description": "Language such as en for english." },
    "layoutX": { "kind": "attribute", "required": "false", "type": "number", "javaType": "java.lang.Double", "deprecated": "true", "secret": "false", "description": "Layout position X" },
    "layoutY": { "kind": "attribute", "required": "false", "type": "number", "javaType": "java.lang.Double", "deprecated": "true", "secret": "false", "description": "Layout position Y" },
    "layoutWidth": { "kind": "attribute", "required": "false", "type": "number", "javaType": "java.lang.Double", "deprecated": "true", "secret": "false", "description": "Layout width" },
    "layoutHeight": { "kind": "attribute", "required": "false", "type": "number", "javaType": "java.lang.Double", "deprecated": "true", "secret": "false", "description": "Layout height" },
    "text": { "kind": "value", "required": "true", "type": "string", "javaType": "java.lang.String", "deprecated": "false", "secret": "false", "description": "The description as human readable text" }
  }
}

